PythonPluginFramework/__init__.py
PythonPluginFramework/app.py
PythonPluginFramework/context.py
PythonPluginFramework/framework.py
PythonPluginFramework/test.py
PythonPluginFramework/test.xml
PythonPluginFramework/configs/__init__.py
PythonPluginFramework/configs/dataservice_config.xml
PythonPluginFramework/plugins/__init__.py
PythonPluginFramework/plugins/RedoUndo/plugin.py
PythonPluginFramework/plugins/appdata/base_data.py
PythonPluginFramework/plugins/appdata/dataservice_reg.py
PythonPluginFramework/plugins/appdata/dataservice_xml.py
PythonPluginFramework/plugins/appdata/plugin.py
PythonPluginFramework/plugins/data_explore/plugin.py
PythonPluginFramework/plugins/data_explore/images/down.png
PythonPluginFramework/plugins/data_explore/images/left.png
PythonPluginFramework/plugins/data_explore/images/right.png
PythonPluginFramework/plugins/data_explore/images/up.png
PythonPluginFramework/plugins/log/plugin.py
PythonPluginFramework/plugins/plugin_explore/plugin.py
PythonPluginFramework/plugins/plugina/plugin.py
PythonPluginFramework/plugins/pluginb/plugin.py
PythonPluginFramework/plugins/property_view/LICENSE
PythonPluginFramework/plugins/property_view/README.md
PythonPluginFramework/plugins/property_view/canvas_typed.py
PythonPluginFramework/plugins/property_view/canvas_variant.py
PythonPluginFramework/plugins/property_view/decoration.py
PythonPluginFramework/plugins/property_view/demo.py
PythonPluginFramework/plugins/property_view/demo_rc.py
PythonPluginFramework/plugins/property_view/extension.py
PythonPluginFramework/plugins/property_view/objectcontroller.py
PythonPluginFramework/plugins/property_view/plugin.py
PythonPluginFramework/plugins/property_view/qtcanvas.py
PythonPluginFramework/plugins/property_view/simple.py
PythonPluginFramework/plugins/property_view/QtProperty/qtbuttonpropertybrowser.py
PythonPluginFramework/plugins/property_view/QtProperty/qteditorfactory.py
PythonPluginFramework/plugins/property_view/QtProperty/qtgroupboxpropertybrowser.py
PythonPluginFramework-0.0.15.dist-info/METADATA
PythonPluginFramework-0.0.15.dist-info/WHEEL
PythonPluginFramework-0.0.15.dist-info/top_level.txt
PythonPluginFramework-0.0.15.dist-info/RECORD
